friday_d33pster-0.2.dist-info/METADATA
friday_d33pster-0.2.dist-info/WHEEL
friday_d33pster-0.2.dist-info/entry_points.txt
friday_d33pster-0.2.dist-info/license_files/LICENSE
Friday/core/lib.py
Friday/core/__init__.py
Friday/core/exceptions/__init__.py
Friday/core/stt_lib.py
Friday/__init__.py
Friday/utils/terminal.py
Friday/utils/__init__.py
Friday/utils/types.py
Friday/friday.py
Friday/rust.cpython-312-darwin.so
friday_d33pster-0.2.dist-info/RECORD
