Metadata-Version: 2.3
Name: friday-d33pster
Version: 0.2
Requires-Dist: gitpython
Requires-Dist: speechrecognition
Requires-Dist: sounddevice
Requires-Dist: numpy
Requires-Dist: pydub
Requires-Dist: pyaudio
Requires-Dist: soundfile
Requires-Dist: requests
Requires-Dist: tqdm
Requires-Dist: wrapper-bar
Requires-Dist: colorama
Requires-Dist: argpi
License-File: LICENSE
Summary: Hey Siri and Ok Google type Voice Assistant implemented in python+rust, Iron Man style!
Project-URL: GitHub, https://github.com/d33pster/Quinn
